pulumi_snowflake/__init__.py
pulumi_snowflake/_inputs.py
pulumi_snowflake/_utilities.py
pulumi_snowflake/account.py
pulumi_snowflake/account_authentication_policy_attachment.py
pulumi_snowflake/account_parameter.py
pulumi_snowflake/account_password_policy_attachment.py
pulumi_snowflake/account_role.py
pulumi_snowflake/alert.py
pulumi_snowflake/api_authentication_integration_with_authorization_code_grant.py
pulumi_snowflake/api_authentication_integration_with_client_credentials.py
pulumi_snowflake/api_authentication_integration_with_jwt_bearer.py
pulumi_snowflake/api_integration.py
pulumi_snowflake/authentication_policy.py
pulumi_snowflake/compute_pool.py
pulumi_snowflake/cortex_search_service.py
pulumi_snowflake/current_account.py
pulumi_snowflake/current_organization_account.py
pulumi_snowflake/database.py
pulumi_snowflake/database_role.py
pulumi_snowflake/dynamic_table.py
pulumi_snowflake/email_notification_integration.py
pulumi_snowflake/execute.py
pulumi_snowflake/external_function.py
pulumi_snowflake/external_oauth_integration.py
pulumi_snowflake/external_table.py
pulumi_snowflake/external_volume.py
pulumi_snowflake/failover_group.py
pulumi_snowflake/file_format.py
pulumi_snowflake/function_java.py
pulumi_snowflake/function_javascript.py
pulumi_snowflake/function_python.py
pulumi_snowflake/function_scala.py
pulumi_snowflake/function_sql.py
pulumi_snowflake/get_account_roles.py
pulumi_snowflake/get_accounts.py
pulumi_snowflake/get_alerts.py
pulumi_snowflake/get_authentication_policies.py
pulumi_snowflake/get_compute_pools.py
pulumi_snowflake/get_connections.py
pulumi_snowflake/get_cortex_search_services.py
pulumi_snowflake/get_current_account.py
pulumi_snowflake/get_current_role.py
pulumi_snowflake/get_database.py
pulumi_snowflake/get_database_role.py
pulumi_snowflake/get_database_roles.py
pulumi_snowflake/get_databases.py
pulumi_snowflake/get_dynamic_tables.py
pulumi_snowflake/get_external_functions.py
pulumi_snowflake/get_external_tables.py
pulumi_snowflake-2.9.1.dist-info/METADATA
pulumi_snowflake-2.9.1.dist-info/WHEEL
pulumi_snowflake-2.9.1.dist-info/top_level.txt
pulumi_snowflake-2.9.1.dist-info/RECORD
